designateclient/__init__.py
designateclient/client.py
designateclient/exceptions.py
designateclient/utils.py
designateclient/version.py
designateclient/functionaltests/__init__.py
designateclient/functionaltests/base.py
designateclient/functionaltests/client.py
designateclient/functionaltests/config.py
designateclient/functionaltests/datagen.py
designateclient/functionaltests/models.py
designateclient/functionaltests/v2/__init__.py
designateclient/functionaltests/v2/fixtures.py
designateclient/functionaltests/v2/test_blacklist.py
designateclient/functionaltests/v2/test_recordsets.py
designateclient/functionaltests/v2/test_shared_zone.py
designateclient/functionaltests/v2/test_tlds.py
designateclient/functionaltests/v2/test_tsigkeys.py
designateclient/functionaltests/v2/test_zone.py
designateclient/functionaltests/v2/test_zone_export.py
designateclient/functionaltests/v2/test_zone_import.py
designateclient/functionaltests/v2/test_zone_transfer.py
designateclient/hacking/__init__.py
designateclient/hacking/checks.py
designateclient/osc/__init__.py
designateclient/osc/plugin.py
designateclient/tests/__init__.py
designateclient/tests/base.py
designateclient/tests/test_designateclient.py
designateclient/tests/test_exceptions.py
designateclient/tests/test_utils.py
designateclient/tests/osc/__init__.py
designateclient/tests/osc/resources/__init__.py
designateclient/tests/osc/resources/recordset_create.json
designateclient/tests/osc/resources/recordset_list.json
designateclient/tests/osc/resources/recordset_list_all.json
designateclient/tests/osc/resources/zone_create.json
designateclient/tests/osc/resources/zone_list.json
designateclient/tests/osc/v2/__init__.py
designateclient/tests/osc/v2/test_recordsets.py
designateclient/tests/osc/v2/test_zone.py
designateclient/tests/v2/__init__.py
designateclient/tests/v2/test_blacklists.py
designateclient/tests/v2/test_client.py
designateclient/tests/v2/test_limits.py
designateclient/tests/v2/test_nameservers.py
python_designateclient-6.3.0.dist-info/AUTHORS
python_designateclient-6.3.0.dist-info/LICENSE
python_designateclient-6.3.0.dist-info/METADATA
python_designateclient-6.3.0.dist-info/WHEEL
python_designateclient-6.3.0.dist-info/entry_points.txt
python_designateclient-6.3.0.dist-info/pbr.json
python_designateclient-6.3.0.dist-info/top_level.txt
python_designateclient-6.3.0.dist-info/RECORD
